__init__.py
core/__init__.py
core/auth/__init__.py
core/utils/__init__.py
domain/__init__.py
domain/entities/__init__.py
domain/interfaces/__init__.py
infrastructure/__init__.py
infrastructure/config/__init__.py
infrastructure/http/__init__.py
pydantic_models/__init__.py
my_dodois_wrapper-0.1.0.dist-info/METADATA
my_dodois_wrapper-0.1.0.dist-info/WHEEL
my_dodois_wrapper-0.1.0.dist-info/top_level.txt
my_dodois_wrapper-0.1.0.dist-info/RECORD
