Metadata-Version: 2.2
Name: my-dodois-wrapper
Version: 0.1.0
Summary: Python-библиотека-обертка для DodoIS API
Author-email: Dodo Samara <youremail@example.com>
License: MIT
Requires-Python: >=3.8
Requires-Dist: httpx>=0.28.1
Requires-Dist: pydantic>=2.10.6
